<?xml version="1.0" encoding="UTF-8"?>
<!DOCTYPE tiles-definitions PUBLIC "-//Apache Software Foundation//DTD Tiles Configuration 3.0//EN" "http://tiles.apache.org/dtds/tiles-config_3_0.dtd">

<tiles-definitions>

    <!-- grupousuario_lista.jsp-->
    <definition name="grupousuario_lista" extends="lte-layout">
        <put-attribute name="body" value="/WEB-INF/views/grupousuario/grupousuario_lista_lte.jsp" />
    </definition>

    <!-- grupousuario_novo.jsp-->
    <definition name="grupousuario_novo" extends="lte-layout">
        <put-attribute name="body" value="/WEB-INF/views/grupousuario/grupousuario_novo_lte.jsp" />
    </definition>

    <!-- grupousuario_editar.jsp-->
    <definition name="grupousuario_editar" extends="lte-layout">
        <put-attribute name="body" value="/WEB-INF/views/grupousuario/grupousuario_editar_lte.jsp" />
    </definition>

    <definition name="grupousuario_detalhes" extends="lte-layout">
        <put-attribute name="body" value="/WEB-INF/views/grupousuario/grupousuario_detalhes_lte.jsp" />
    </definition>




    <definition name="usuariodogrupo_novo" extends="lte-layout">
        <put-attribute name="body" value="/WEB-INF/views/grupousuario/usuariodogrupo_novo_lte.jsp" />
    </definition>

    <definition name="grupotransacao_novo" extends="lte-layout">
        <put-attribute name="body" value="/WEB-INF/views/grupousuario/grupotransacao_novo_lte.jsp" />
    </definition>

    <definition name="empresagrupo_novo" extends="lte-layout">
        <put-attribute name="body" value="/WEB-INF/views/grupousuario/empresagrupo_novo_lte.jsp" />
    </definition>

</tiles-definitions>